edgegallery_sdk_face_recognition/__init__.py
edgegallery_sdk_face_recognition/api/__init__.py
edgegallery_sdk_face_recognition/api/default_api.py
edgegallery_sdk_face_recognition/api/recognition_api.py
edgegallery_sdk_face_recognition/api/upload_api.py
edgegallery_sdk_face_recognition/api/video_api.py
test/__init__.py
test/test_body.py
test/test_body1.py
test/test_body2.py
test/test_default_api.py
test/test_recognition_api.py
test/test_upload_api.py
test/test_video_api.py
edgegallery_sdk_face_recognition-1.4.dist-info/METADATA
edgegallery_sdk_face_recognition-1.4.dist-info/WHEEL
edgegallery_sdk_face_recognition-1.4.dist-info/top_level.txt
edgegallery_sdk_face_recognition-1.4.dist-info/RECORD
